simpletcpclient/VERSION
simpletcpclient/__init__.py
simpletcpclient/__main__.py
simpletcpclient-1.0.1.dist-info/METADATA
simpletcpclient-1.0.1.dist-info/WHEEL
simpletcpclient-1.0.1.dist-info/entry_points.txt
simpletcpclient-1.0.1.dist-info/licenses/LICENSE
simpletcpclient-1.0.1.dist-info/RECORD
