Metadata-Version: 2.1
Name: simpletcpclient
Version: 1.0.1
Summary: Simple command line TCP client
Project-URL: Homepage, https://gitlab.cylab.be/cylab/simpletcpclient
Project-URL: Bug Tracker, https://gitlab.cylab.be/cylab/simpletcpclient/-/issues
Author-email: Thibault Debatty <t.debatty@cylab.be>
License-File: LICENSE
Classifier: License :: OSI Approved :: MIT License
Classifier: Operating System :: OS Independent
Classifier: Programming Language :: Python :: 3
Requires-Python: >=3.7
Requires-Dist: pyreadline3
Requires-Dist: validators
